essHIC/__init__.py
essHIC/dist.py
essHIC/ess.py
essHIC/hic.py
essHIC/make_hic.py
essHIC/utils.py
essHIC-1.44.dist-info/METADATA
essHIC-1.44.dist-info/WHEEL
essHIC-1.44.dist-info/top_level.txt
essHIC-1.44.dist-info/zip-safe
essHIC-1.44.dist-info/RECORD
